anyeq_r1shy/__init__.py
anyeq_r1shy/anyeq.py
anyeq_r1shy-0.0.1.dist-info/licenses/LICENSE
anyeq_r1shy-0.0.1.dist-info/WHEEL
anyeq_r1shy-0.0.1.dist-info/METADATA
anyeq_r1shy-0.0.1.dist-info/RECORD
