Metadata-Version: 2.4
Name: anyeq-r1shy
Version: 0.0.1
Summary: A simple lib to check if any values in a list are equal to a value
Author: Emma Kadlecek
Author-email: Emma Kadlecek <kadlecekemma@gmail.com>
License-Expression: MIT
License-File: LICENSE
Classifier: Programming Language :: Python :: 3
Classifier: Operating System :: OS Independent
Requires-Python: >=3.9
